pddlgym/__init__.py
pddlgym/core.py
pddlgym/demo.py
pddlgym/inference.py
pddlgym/parser.py
pddlgym/planning.py
pddlgym/spaces.py
pddlgym/structs.py
pddlgym/utils.py
pddlgym/pddl/backup_depot.pddl
pddlgym/pddl/baking.pddl
pddlgym/pddl/blocks.pddl
pddlgym/pddl/blocks_operator_actions.pddl
pddlgym/pddl/conditionalblocks.pddl
pddlgym/pddl/conditionalferry.pddl
pddlgym/pddl/depot.pddl
pddlgym/pddl/doors.pddl
pddlgym/pddl/easyblocks.pddl
pddlgym/pddl/elevator.pddl
pddlgym/pddl/explodingblocks.pddl
pddlgym/pddl/ferry.pddl
pddlgym/pddl/glibblocks.pddl
pddlgym/pddl/glibdoors.pddl
pddlgym/pddl/glibrearrangement.pddl
pddlgym/pddl/hanoi.pddl
pddlgym/pddl/meetpass.pddl
pddlgym/pddl/minecraft.pddl
pddlgym/pddl/rearrangement-notyping.pddl
pddlgym/pddl/rearrangement.pddl
pddlgym/pddl/river.pddl
pddlgym/pddl/slidetile.pddl
pddlgym/pddl/sokoban.pddl
pddlgym/pddl/tireworld.pddl
pddlgym/pddl/travel.pddl
pddlgym/pddl/travelhard.pddl
pddlgym/pddl/tsp.pddl
pddlgym/pddl/baking/problem0.pddl
pddlgym/pddl/baking/problem2.pddl
pddlgym/pddl/baking/problem4.pddl
pddlgym/pddl/baking/problem6.pddl
pddlgym/pddl/baking_test/problem1.pddl
pddlgym/pddl/baking_test/problem3.pddl
pddlgym/pddl/baking_test/problem5.pddl
pddlgym/pddl/baking_test/problem7.pddl
pddlgym/pddl/blocks/problem1.pddl
pddlgym/pddl/blocks/problem3.pddl
pddlgym/pddl/blocks/problem5.pddl
pddlgym/pddl/blocks/problem7.pddl
pddlgym/pddl/blocks/problem9.pddl
pddlgym/pddl/blocks_operator_actions/problem1.pddl
pddlgym/pddl/blocks_test/problem10.pddl
pddlgym/pddl/blocks_test/problem2.pddl
pddlgym/pddl/blocks_test/problem4.pddl
pddlgym/pddl/blocks_test/problem6.pddl
pddlgym/pddl/blocks_test/problem8.pddl
pddlgym/pddl/conditionalblocks/problem1.pddl
pddlgym/pddl/conditionalblocks/problem3.pddl
pddlgym/pddl/conditionalblocks/problem5.pddl
pddlgym/pddl/conditionalblocks/problem7.pddl
pddlgym/pddl/conditionalblocks/problem9.pddl
pddlgym/pddl/conditionalblocks_test/problem10.pddl
pddlgym/pddl/conditionalblocks_test/problem2.pddl
pddlgym-0.0.1.dist-info/METADATA
pddlgym-0.0.1.dist-info/WHEEL
pddlgym-0.0.1.dist-info/top_level.txt
pddlgym-0.0.1.dist-info/RECORD
