Metadata-Version: 2.1
Name: pddlgym
Version: 0.0.1
Summary: UNKNOWN
Home-page: UNKNOWN
Author: UNKNOWN
Author-email: UNKNOWN
License: UNKNOWN
Platform: UNKNOWN
Requires-Dist: matplotlib
Requires-Dist: pillow
Requires-Dist: gym
Requires-Dist: imageio
Requires-Dist: pyperplan
